jet/__init__.py
jet/admin.py
jet/filters.py
jet/forms.py
jet/models.py
jet/ordered_set.py
jet/settings.py
jet/urls.py
jet/utils.py
jet/views.py
jet/dashboard/__init__.py
jet/dashboard/dashboard.py
jet/dashboard/forms.py
jet/dashboard/models.py
jet/dashboard/modules.py
jet/dashboard/settings.py
jet/dashboard/urls.py
jet/dashboard/utils.py
jet/dashboard/views.py
jet/dashboard/dashboard_modules/__init__.py
jet/dashboard/dashboard_modules/google_analytics.py
jet/dashboard/dashboard_modules/google_analytics_views.py
jet/dashboard/dashboard_modules/yandex_metrika.py
jet/dashboard/dashboard_modules/yandex_metrika_views.py
jet/dashboard/locale/ar/LC_MESSAGES/django.mo
jet/dashboard/locale/ar/LC_MESSAGES/django.po
jet/dashboard/locale/ar/LC_MESSAGES/djangojs.mo
jet/dashboard/locale/ar/LC_MESSAGES/djangojs.po
jet/dashboard/locale/cs/LC_MESSAGES/django.mo
jet/dashboard/locale/cs/LC_MESSAGES/django.po
jet/dashboard/locale/cs/LC_MESSAGES/djangojs.mo
jet/dashboard/locale/cs/LC_MESSAGES/djangojs.po
jet/dashboard/locale/de/LC_MESSAGES/django.mo
jet/dashboard/locale/de/LC_MESSAGES/django.po
jet/dashboard/locale/de/LC_MESSAGES/djangojs.mo
jet/dashboard/locale/de/LC_MESSAGES/djangojs.po
jet/dashboard/locale/en/LC_MESSAGES/django.mo
jet/dashboard/locale/en/LC_MESSAGES/django.po
jet/dashboard/locale/en/LC_MESSAGES/djangojs.mo
jet/dashboard/locale/en/LC_MESSAGES/djangojs.po
jet/dashboard/locale/es/LC_MESSAGES/django.mo
jet/dashboard/locale/es/LC_MESSAGES/django.po
jet/dashboard/locale/es/LC_MESSAGES/djangojs.mo
jet/dashboard/locale/es/LC_MESSAGES/djangojs.po
jet/dashboard/locale/fa/LC_MESSAGES/django.po
jet/dashboard/locale/fa/LC_MESSAGES/djangojs.po
jet/dashboard/locale/fr/LC_MESSAGES/django.po
jet/dashboard/locale/fr/LC_MESSAGES/djangojs.po
jet/dashboard/locale/pl/LC_MESSAGES/django.mo
jet/dashboard/locale/pl/LC_MESSAGES/django.po
jet/dashboard/locale/pt-br/LC_MESSAGES/django.mo
jet/dashboard/locale/pt-br/LC_MESSAGES/django.po
jet/dashboard/locale/pt-br/LC_MESSAGES/djangojs.mo
django_jet_reborn-1.3.6.dist-info/LICENSE
django_jet_reborn-1.3.6.dist-info/METADATA
django_jet_reborn-1.3.6.dist-info/WHEEL
django_jet_reborn-1.3.6.dist-info/top_level.txt
django_jet_reborn-1.3.6.dist-info/RECORD
